sql_to_lnh/CodeGenerator.py
sql_to_lnh/CogPrinter.py
sql_to_lnh/LambdaDict.py
sql_to_lnh/SqliteContext.py
sql_to_lnh/Static.py
sql_to_lnh/Transformer.py
sql_to_lnh/TypeConverter.py
sql_to_lnh/Visitor.py
sql_to_lnh/__init__.py
sql_to_lnh/utils.py
sql_to_lnh/cli/__init__.py
sql_to_lnh/cli/main.py
sql_to_lnh/generated/SQLiteLexer.py
sql_to_lnh/generated/SQLiteParser.py
sql_to_lnh/generated/SQLiteParserListener.py
sql_to_lnh/generated/SQLiteParserVisitor.py
sql_to_lnh/generated/__init__.py
sql_to_lnh/transformers/CreateTableTransformer.py
sql_to_lnh/transformers/InsertTransformer.py
sql_to_lnh/transformers/SelectTransformer.py
sql_to_lnh/transformers/__init__.py
sql_to_lnh-1.0.1.dist-info/LICENSE
sql_to_lnh-1.0.1.dist-info/METADATA
sql_to_lnh-1.0.1.dist-info/WHEEL
sql_to_lnh-1.0.1.dist-info/entry_points.txt
sql_to_lnh-1.0.1.dist-info/top_level.txt
sql_to_lnh-1.0.1.dist-info/RECORD
