Metadata-Version: 2.1
Name: sql_to_lnh
Version: 1.0.1
Summary: SQL to LNH allows to generate LNH structures and functions from SQL queries.
Author-email: Mikhail Geine <mike.geine@gmail.com>, Kirill Dremin <missl.wipiece@gmail.com>
License: MIT License
Project-URL: Repository, https://latex.bmstu.ru/gitlab/teragraph/leonhard_euler/sql_to_lnh
Project-URL: Issues, https://latex.bmstu.ru/gitlab/teragraph/leonhard_euler/sql_to_lnh/issues
Classifier: Development Status :: 5 - Production/Stable
Classifier: Intended Audience :: Science/Research
Classifier: License :: OSI Approved :: MIT License
Classifier: Operating System :: POSIX :: Linux
Classifier: Programming Language :: Python :: 3.10
License-File: LICENSE
Requires-Dist: antlr4-python3-runtime ==4.13.0
Requires-Dist: cogapp
